Workbook

Sheet Como usar
A1: Comparar outro banco com o Growths
A3: 1. No outro banco, rode a consulta abaixo (funciona em PostgreSQL, Supabase, MySQL e SQL Server, que têm information_schema).
A4: 2. Copie o resultado (4 colunas: tabela, coluna, tipo, obrigatório) e cole na aba "Outro banco", a partir da linha 2 (por cima do texto cinza).
A5: 3. Na aba "Comparação", cada campo do outro banco aparece com o campo do Growths de mesmo nome e um status:
A6: • Importa direto: o Growths tem a coluna e o tipo é compatível.
A7: • Ajustar tipo: o Growths tem a coluna, mas o tipo é diferente (ex.: texto → número, data guardada como texto).
A8: • Sem campo no Growths: não existe com esse nome. Se for o mesmo dado com outro nome, escreva a tabela e a coluna do Growths nas colunas amarelas (E e F).
A9: • Sem tabela no Growths: a tabela não existe com esse nome. Escreva a tabela do Growths equivalente na coluna E.
A10: 4. Na aba "Campos Growths", a coluna "Vem do outro banco?" mostra quais campos do Growths vão receber dados. "FALTA (obrigatória)" = campo obrigatório sem origem: precisa de valor padrão ou regra na importação.
A11: 5. "Valores aceitos (CHECK)" e "Liga com (FK)" mostram o que precisa ser convertido. Ex.: status "Ativo" no outro banco precisa virar "ativo"; o cliente precisa existir em pessoas antes da venda.
A12: 6. A aba "Tipos" diz quais tipos são compatíveis entre si. Se aparecer "outro", acrescente o tipo lá com a família certa.
A14: Consulta para rodar no outro banco:
... A20: Resumo da comparação (atualiza sozinho):
A21: ="Importa direto: "&COUNTIF(Comparação!$L:$L,"Importa direto") -> Importa direto: 0
A22: ="Ajustar tipo: "&COUNTIF(Comparação!$L:$L,"Ajustar tipo") -> Ajustar tipo: 0
A23: ="Sem campo no Growths: "&COUNTIF(Comparação!$L:$L,"Sem campo no Growths") -> Sem campo no Growths: 0
A24: ="Sem tabela no Growths: "&COUNTIF(Comparação!$L:$L,"Sem tabela no Growths") -> Sem tabela no Growths: 0
A25: ="Campos obrigatórios do Growths sem origem: "&COUNTIF('Campos Growths'!$M:$M,"FALTA*")&" (filtre a aba Campos Growths pelas tabelas que vai importar)" -> Campos obrigatórios do Growths sem origem: 438 (filtre a aba Campos Growths pelas tabelas que vai importar)
A27: Fonte: banco de produção do Growths (projeto yngyghlyonybvfvjcmxl) em 17/10/2026: 134 tabelas e 1502 colunas. Estrutura completa em Growths_estrutura_tabelas.sql.

Sheet Tabelas
A1: Tabela | B1: Módulo | C1: Colunas | D1: Obrigatórias | E1: Liga com (FK)
A2: acesso_telas | B2: Acessos | C2: 5 | D2: 4
A3: aluno_historico | B3: Clientes e alunos | C3: 7 | D3: 5 | E3: alunos, etapas_kanban, pessoas, workspaces
A4: alunos | B4: Clientes e alunos | C4: 13 | D4: 8 | E4: contratos, equipe, etapas_kanban, pessoas, produtos, vendas, workspaces
A5: anuncios | B5: Marketing e campanhas | C5: 10 | D5: 6 | E5: campanha_canais, workspaces
A6: auditoria | B6: Sistema | C6: 12 | D6: 5
A7: benchmarks_mercado | B7: Planejamento | C7: 6 | D7: 5 | E7: workspaces
A8: campanha_blocos | B8: Marketing e campanhas | C8: 11 | D8: 9 | E8: campanhas, workspaces
A9: campanha_calculos | B9: Marketing e campanhas | C9: 7 | D9: 6 | E9: campanhas, workspaces
A10: campanha_canais | B10: Marketing e campanhas | C10: 16 | D10: 5 | E10: campanhas, canais, funis, workspaces
A11: campanha_debriefing | B11: Marketing e campanhas | C11: 9 | D11: 4 | E11: campanhas, workspaces
A12: campanha_estrategias | B12: Marketing e campanhas | C12: 6 | D12: 6 | E12: campanhas, funis, workspaces
A13: campanha_etapa_valores | B13: Marketing e campanhas | C13: 9 | D13: 8 | E13: campanha_etapas, workspaces
A14: campanha_etapas | B14: Marketing e campanhas | C14: 18 | D14: 11 | E14: campanha_blocos, campanhas, workspaces
A15: campanha_fechamentos | B15: Marketing e campanhas | C15: 15 | D15: 6 | E15: campanha_fechamentos, campanhas, workspaces
A16: campanha_links | B16: Marketing e campanhas | C16: 13 | D16: 10 | E16: anuncios, campanha_canais, workspaces
A17: campanha_melhorias | B17: Marketing e campanhas | C17: 12 | D17: 8 | E17: campanhas, workspaces
A18: campanha_metas | B18: Marketing e campanhas | C18: 13 | D18: 6 | E18: campanhas, workspaces
... A79: metricas_anuncio_dia | B79: Marketing e campanhas | C79: 13 | D79: 10 | E79: anuncios, importacoes, workspaces
A80: metricas_definicoes | B80: Sistema | C80: 8 | D80: 7
A81: motivos_resultado | B81: Pessoas e CRM | C81: 5 | D81: 5 | E81: workspaces
A82: movimentacoes_bancarias | B82: Financeiro | C82: 10 | D82: 6 | E82: contas_bancarias, lancamentos, workspaces
A83: notificacoes | B83: Acessos | C83: 15 | D83: 9 | E83: equipe, pessoas, projeto_atividades, projetos, workspaces
A84: oferta_itens | B84: Produtos e ofertas | C84: 6 | D84: 6 | E84: ofertas, produtos, workspaces
A85: oferta_versoes | B85: Produtos e ofertas | C85: 11 | D85: 8 | E85: ofertas, workspaces
A86: ofertas | B86: Produtos e ofertas | C86: 15 | D86: 9 | E86: produtos, workspaces
A87: oportunidades | B87: Pessoas e CRM | C87: 16 | D87: 7 | E87: contratos, equipe, etapas_kanban, pessoas, produtos, workspaces
A88: pacotes_acesso | B88: Acessos | C88: 7 | D88: 6
A89: pagamentos_historicos | B89: Financeiro | C89: 10 | D89: 5 | E89: pessoas, produtos, workspaces
A90: partidas | B90: Financeiro | C90: 7 | D90: 6 | E90: centros_custo, lancamentos, plano_contas, workspaces
A91: pesquisa_envios | B91: Pesquisas | C91: 11 | D91: 8 | E91: pesquisas, pessoas, workspaces
A92: pesquisa_insights | B92: Pesquisas | C92: 7 | D92: 5 | E92: growth_metricas, pesquisa_perguntas, pesquisas, workspaces
A93: pesquisa_perguntas | B93: Pesquisas | C93: 10 | D93: 10 | E93: pesquisas, workspaces
A94: pesquisa_resposta_itens | B94: Pesquisas | C94: 6 | D94: 4 | E94: pesquisa_perguntas, pesquisa_respostas, workspaces
A95: pesquisa_respostas | B95: Pesquisas | C95: 7 | D95: 4 | E95: pesquisa_envios, pesquisas, pessoas, workspaces
A96: pesquisas | B96: Pesquisas | C96: 15 | D96: 11 | E96: funis, workspaces
A97: pessoa_funil | B97: Pessoas e CRM | C97: 7 | D97: 7 | E97: funil_etapas, funis, pessoas, workspaces
A98: pessoa_funil_historico | B98: Pessoas e CRM | C98: 9 | D98: 6 | E98: funis, pessoas, workspaces
A99: pessoa_historico | B99: Pessoas e CRM | C99: 7 | D99: 5 | E99: pessoas
A100: pessoa_lista | B100: Pessoas e CRM | C100: 6 | D100: 5 | E100: funil_listas, pessoas, workspaces
... A135: workspaces | B135: Acessos | C135: 11 | D135: 9 | E135: pacotes_acesso, workspaces

Sheet Campos Growths
A1: Chave | B1: Tabela | C1: Módulo | D1: Ordem | E1: Coluna | F1: Tipo | G1: Obrigatória | H1: Padrão / cálculo | I1: PK / única | J1: Liga com (FK) | K1: Valores aceitos (CHECK) | L1: Família do tipo | M1: Vem do outro banco?
A2: =B2&"."&E2 -> acesso_telas.tela | B2: acesso_telas | C2: Acessos | D2: 1 | E2: tela | F2: text | G2: sim | I2: PRIMARY KEY | L2: =IFERROR(VLOOKUP(IF(ISNUMBER(SEARCH("(",F2)),LEFT(F2,SEARCH("(",F2)-1),F2),Tipos!$A:$B,2,FALSE()),"outro") -> texto | M2: =IF(COUNTIF(Comparação!$H:$H,A2)>0,"sim",IF(AND(G2="sim",H2=""),"FALTA (obrigatória)","não")) -> FALTA (obrigatória)
A3: =B3&"."&E3 -> acesso_telas.modulo | B3: acesso_telas | C3: Acessos | D3: 2 | E3: modulo | F3: text | G3: sim | L3: =IFERROR(VLOOKUP(IF(ISNUMBER(SEARCH("(",F3)),LEFT(F3,SEARCH("(",F3)-1),F3),Tipos!$A:$B,2,FALSE()),"outro") -> texto | M3: =IF(COUNTIF(Comparação!$H:$H,A3)>0,"sim",IF(AND(G3="sim",H3=""),"FALTA (obrigatória)","não")) -> FALTA (obrigatória)
A4: =B4&"."&E4 -> acesso_telas.nome | B4: acesso_telas | C4: Acessos | D4: 3 | E4: nome | F4: text | G4: sim | L4: =IFERROR(VLOOKUP(IF(ISNUMBER(SEARCH("(",F4)),LEFT(F4,SEARCH("(",F4)-1),F4),Tipos!$A:$B,2,FALSE()),"outro") -> texto | M4: =IF(COUNTIF(Comparação!$H:$H,A4)>0,"sim",IF(AND(G4="sim",H4=""),"FALTA (obrigatória)","não")) -> FALTA (obrigatória)
A5: =B5&"."&E5 -> acesso_telas.grupo | B5: acesso_telas | C5: Acessos | D5: 4 | E5: grupo | F5: text | G5: não | L5: =IFERROR(VLOOKUP(IF(ISNUMBER(SEARCH("(",F5)),LEFT(F5,SEARCH("(",F5)-1),F5),Tipos!$A:$B,2,FALSE()),"outro") -> texto | M5: =IF(COUNTIF(Comparação!$H:$H,A5)>0,"sim",IF(AND(G5="sim",H5=""),"FALTA (obrigatória)","não")) -> não
A6: =B6&"."&E6 -> acesso_telas.ordem | B6: acesso_telas | C6: Acessos | D6: 5 | E6: ordem | F6: integer | G6: sim | H6: 0 | L6: =IFERROR(VLOOKUP(IF(ISNUMBER(SEARCH("(",F6)),LEFT(F6,SEARCH("(",F6)-1),F6),Tipos!$A:$B,2,FALSE()),"outro") -> inteiro | M6: =IF(COUNTIF(Comparação!$H:$H,A6)>0,"sim",IF(AND(G6="sim",H6=""),"FALTA (obrigatória)","não")) -> não
A7: =B7&"."&E7 -> aluno_historico.id | B7: aluno_historico | C7: Clientes e alunos | D7: 1 | E7: id | F7: uuid | G7: sim | H7: gen_random_uuid() | I7: PRIMARY KEY | L7: =IFERROR(VLOOKUP(IF(ISNUMBER(SEARCH("(",F7)),LEFT(F7,SEARCH("(",F7)-1),F7),Tipos!$A:$B,2,FALSE()),"outro") -> uuid | M7: =IF(COUNTIF(Comparação!$H:$H,A7)>0,"sim",IF(AND(G7="sim",H7=""),"FALTA (obrigatória)","não")) -> não
A8: =B8&"."&E8 -> aluno_historico.workspace_id | B8: aluno_historico | C8: Clientes e alunos | D8: 2 | E8: workspace_id | F8: uuid | G8: sim | J8: workspaces.id | L8: =IFERROR(VLOOKUP(IF(ISNUMBER(SEARCH("(",F8)),LEFT(F8,SEARCH("(",F8)-1),F8),Tipos!$A:$B,2,FALSE()),"outro") -> uuid | M8: =IF(COUNTIF(Comparação!$H:$H,A8)>0,"sim",IF(AND(G8="sim",H8=""),"FALTA (obrigatória)","não")) -> FALTA (obrigatória)
A9: =B9&"."&E9 -> aluno_historico.aluno_id | B9: aluno_historico | C9: Clientes e alunos | D9: 3 | E9: aluno_id | F9: uuid | G9: sim | J9: alunos.id | L9: =IFERROR(VLOOKUP(IF(ISNUMBER(SEARCH("(",F9)),LEFT(F9,SEARCH("(",F9)-1),F9),Tipos!$A:$B,2,FALSE()),"outro") -> uuid | M9: =IF(COUNTIF(Comparação!$H:$H,A9)>0,"sim",IF(AND(G9="sim",H9=""),"FALTA (obrigatória)","não")) -> FALTA (obrigatória)
A10: =B10&"."&E10 -> aluno_historico.pessoa_id | B10: aluno_historico | C10: Clientes e alunos | D10: 4 | E10: pessoa_id | F10: uuid | G10: não | J10: pessoas.id | L10: =IFERROR(VLOOKUP(IF(ISNUMBER(SEARCH("(",F10)),LEFT(F10,SEARCH("(",F10)-1),F10),Tipos!$A:$B,2,FALSE()),"outro") -> uuid | M10: =IF(COUNTIF(Comparação!$H:$H,A10)>0,"sim",IF(AND(G10="sim",H10=""),"FALTA (obrigatória)","não")) -> não
A11: =B11&"."&E11 -> aluno_historico.tipo | B11: aluno_historico | C11: Clientes e alunos | D11: 5 | E11: tipo | F11: text | G11: sim | K11: CHECK ((tipo = ANY (ARRAY['etapa'::text, 'saida'::text, 'volta'::text]))) | L11: =IFERROR(VLOOKUP(IF(ISNUMBER(SEARCH("(",F11)),LEFT(F11,SEARCH("(",F11)-1),F11),Tipos!$A:$B,2,FALSE()),"outro") -> texto | M11: =IF(COUNTIF(Comparação!$H:$H,A11)>0,"sim",IF(AND(G11="sim",H11=""),"FALTA (obrigatória)","não")) -> FALTA (obrigatória)
A12: =B12&"."&E12 -> aluno_historico.etapa_kanban_id | B12: aluno_historico | C12: Clientes e alunos | D12: 6 | E12: etapa_kanban_id | F12: uuid | G12: não | J12: etapas_kanban.id | L12: =IFERROR(VLOOKUP(IF(ISNUMBER(SEARCH("(",F12)),LEFT(F12,SEARCH("(",F12)-1),F12),Tipos!$A:$B,2,FALSE()),"outro") -> uuid | M12: =IF(COUNTIF(Comparação!$H:$H,A12)>0,"sim",IF(AND(G12="sim",H12=""),"FALTA (obrigatória)","não")) -> não
A13: =B13&"."&E13 -> aluno_historico.em | B13: aluno_historico | C13: Clientes e alunos | D13: 7 | E13: em | F13: timestamptz | G13: sim | H13: now() | L13: =IFERROR(VLOOKUP(IF(ISNUMBER(SEARCH("(",F13)),LEFT(F13,SEARCH("(",F13)-1),F13),Tipos!$A:$B,2,FALSE()),"outro") -> data e hora | M13: =IF(COUNTIF(Comparação!$H:$H,A13)>0,"sim",IF(AND(G13="sim",H13=""),"FALTA (obrigatória)","não")) -> não
A14: =B14&"."&E14 -> alunos.id | B14: alunos | C14: Clientes e alunos | D14: 1 | E14: id | F14: uuid | G14: sim | H14: gen_random_uuid() | I14: PRIMARY KEY | L14: =IFERROR(VLOOKUP(IF(ISNUMBER(SEARCH("(",F14)),LEFT(F14,SEARCH("(",F14)-1),F14),Tipos!$A:$B,2,FALSE()),"outro") -> uuid | M14: =IF(COUNTIF(Comparação!$H:$H,A14)>0,"sim",IF(AND(G14="sim",H14=""),"FALTA (obrigatória)","não")) -> não
A15: =B15&"."&E15 -> alunos.workspace_id | B15: alunos | C15: Clientes e alunos | D15: 2 | E15: workspace_id | F15: uuid | G15: sim | J15: workspaces.id | L15: =IFERROR(VLOOKUP(IF(ISNUMBER(SEARCH("(",F15)),LEFT(F15,SEARCH("(",F15)-1),F15),Tipos!$A:$B,2,FALSE()),"outro") -> uuid | M15: =IF(COUNTIF(Comparação!$H:$H,A15)>0,"sim",IF(AND(G15="sim",H15=""),"FALTA (obrigatória)","não")) -> FALTA (obrigatória)
A16: =B16&"."&E16 -> alunos.pessoa_id | B16: alunos | C16: Clientes e alunos | D16: 3 | E16: pessoa_id | F16: uuid | G16: sim | J16: pessoas.id | L16: =IFERROR(VLOOKUP(IF(ISNUMBER(SEARCH("(",F16)),LEFT(F16,SEARCH("(",F16)-1),F16),Tipos!$A:$B,2,FALSE()),"outro") -> uuid | M16: =IF(COUNTIF(Comparação!$H:$H,A16)>0,"sim",IF(AND(G16="sim",H16=""),"FALTA (obrigatória)","não")) -> FALTA (obrigatória)
A17: =B17&"."&E17 -> alunos.produto_id | B17: alunos | C17: Clientes e alunos | D17: 4 | E17: produto_id | F17: uuid | G17: sim | J17: produtos.id | L17: =IFERROR(VLOOKUP(IF(ISNUMBER(SEARCH("(",F17)),LEFT(F17,SEARCH("(",F17)-1),F17),Tipos!$A:$B,2,FALSE()),"outro") -> uuid | M17: =IF(COUNTIF(Comparação!$H:$H,A17)>0,"sim",IF(AND(G17="sim",H17=""),"FALTA (obrigatória)","não")) -> FALTA (obrigatória)
A18: =B18&"."&E18 -> alunos.venda_id | B18: alunos | C18: Clientes e alunos | D18: 5 | E18: venda_id | F18: uuid | G18: não | I18: UNIQUE | J18: vendas.id | L18: =IFERROR(VLOOKUP(IF(ISNUMBER(SEARCH("(",F18)),LEFT(F18,SEARCH("(",F18)-1),F18),Tipos!$A:$B,2,FALSE()),"outro") -> uuid | M18: =IF(COUNTIF(Comparação!$H:$H,A18)>0,"sim",IF(AND(G18="sim",H18=""),"FALTA (obrigatória)","não")) -> não
A19: =B19&"."&E19 -> alunos.tag | B19: alunos | C19: Clientes e alunos | D19: 6 | E19: tag | F19: text | G19: sim | L19: =IFERROR(VLOOKUP(IF(ISNUMBER(SEARCH("(",F19)),LEFT(F19,SEARCH("(",F19)-1),F19),Tipos!$A:$B,2,FALSE()),"outro") -> texto | M19: =IF(COUNTIF(Comparação!$H:$H,A19)>0,"sim",IF(AND(G19="sim",H19=""),"FALTA (obrigatória)","não")) -> FALTA (obrigatória)
A20: =B20&"."&E20 -> alunos.etapa_kanban_id | B20: alunos | C20: Clientes e alunos | D20: 7 | E20: etapa_kanban_id | F20: uuid | G20: não | J20: etapas_kanban.id | L20: =IFERROR(VLOOKUP(IF(ISNUMBER(SEARCH("(",F20)),LEFT(F20,SEARCH("(",F20)-1),F20),Tipos!$A:$B,2,FALSE()),"outro") -> uuid | M20: =IF(COUNTIF(Comparação!$H:$H,A20)>0,"sim",IF(AND(G20="sim",H20=""),"FALTA (obrigatória)","não")) -> não
A21: =B21&"."&E21 -> alunos.status | B21: alunos | C21: Clientes e alunos | D21: 8 | E21: status | F21: text | G21: sim | H21: 'ativo'::text | K21: CHECK ((status = ANY (ARRAY['ativo'::text, 'inativo'::text, 'cancelado'::text]))) | L21: =IFERROR(VLOOKUP(IF(ISNUMBER(SEARCH("(",F21)),LEFT(F21,SEARCH("(",F21)-1),F21),Tipos!$A:$B,2,FALSE()),"outro") -> texto | M21: =IF(COUNTIF(Comparação!$H:$H,A21)>0,"sim",IF(AND(G21="sim",H21=""),"FALTA (obrigatória)","não")) -> não
A22: =B22&"."&E22 -> alunos.entrou_em | B22: alunos | C22: Clientes e alunos | D22: 9 | E22: entrou_em | F22: timestamptz | G22: sim | H22: now() | L22: =IFERROR(VLOOKUP(IF(ISNUMBER(SEARCH("(",F22)),LEFT(F22,SEARCH("(",F22)-1),F22),Tipos!$A:$B,2,FALSE()),"outro") -> data e hora | M22: =IF(COUNTIF(Comparação!$H:$H,A22)>0,"sim",IF(AND(G22="sim",H22=""),"FALTA (obrigatória)","não")) -> não
A23: =B23&"."&E23 -> alunos.saiu_em | B23: alunos | C23: Clientes e alunos | D23: 10 | E23: saiu_em | F23: timestamptz | G23: não | L23: =IFERROR(VLOOKUP(IF(ISNUMBER(SEARCH("(",F23)),LEFT(F23,SEARCH("(",F23)-1),F23),Tipos!$A:$B,2,FALSE()),"outro") -> data e hora | M23: =IF(COUNTIF(Comparação!$H:$H,A23)>0,"sim",IF(AND(G23="sim",H23=""),"FALTA (obrigatória)","não")) -> não
A24: =B24&"."&E24 -> alunos.responsavel_cs_id | B24: alunos | C24: Clientes e alunos | D24: 11 | E24: responsavel_cs_id | F24: uuid | G24: não | J24: equipe.id | L24: =IFERROR(VLOOKUP(IF(ISNUMBER(SEARCH("(",F24)),LEFT(F24,SEARCH("(",F24)-1),F24),Tipos!$A:$B,2,FALSE()),"outro") -> uuid | M24: =IF(COUNTIF(Comparação!$H:$H,A24)>0,"sim",IF(AND(G24="sim",H24=""),"FALTA (obrigatória)","não")) -> não
A25: =B25&"."&E25 -> alunos.contrato_id | B25: alunos | C25: Clientes e alunos | D25: 12 | E25: contrato_id | F25: uuid | G25: não | J25: contratos.id | L25: =IFERROR(VLOOKUP(IF(ISNUMBER(SEARCH("(",F25)),LEFT(F25,SEARCH("(",F25)-1),F25),Tipos!$A:$B,2,FALSE()),"outro") -> uuid | M25: =IF(COUNTIF(Comparação!$H:$H,A25)>0,"sim",IF(AND(G25="sim",H25=""),"FALTA (obrigatória)","não")) -> não
A26: =B26&"."&E26 -> alunos.origem | B26: alunos | C26: Clientes e alunos | D26: 13 | E26: origem | F26: text | G26: sim | H26: 'venda'::text | L26: =IFERROR(VLOOKUP(IF(ISNUMBER(SEARCH("(",F26)),LEFT(F26,SEARCH("(",F26)-1),F26),Tipos!$A:$B,2,FALSE()),"outro") -> texto | M26: =IF(COUNTIF(Comparação!$H:$H,A26)>0,"sim",IF(AND(G26="sim",H26=""),"FALTA (obrigatória)","não")) -> não
A27: =B27&"."&E27 -> anuncios.id | B27: anuncios | C27: Marketing e campanhas | D27: 1 | E27: id | F27: uuid | G27: sim | H27: gen_random_uuid() | I27: PRIMARY KEY | L27: =IFERROR(VLOOKUP(IF(ISNUMBER(SEARCH("(",F27)),LEFT(F27,SEARCH("(",F27)-1),F27),Tipos!$A:$B,2,FALSE()),"outro") -> uuid | M27: =IF(COUNTIF(Comparação!$H:$H,A27)>0,"sim",IF(AND(G27="sim",H27=""),"FALTA (obrigatória)","não")) -> não
A28: =B28&"."&E28 -> anuncios.workspace_id | B28: anuncios | C28: Marketing e campanhas | D28: 2 | E28: workspace_id | F28: uuid | G28: sim | J28: workspaces.id | L28: =IFERROR(VLOOKUP(IF(ISNUMBER(SEARCH("(",F28)),LEFT(F28,SEARCH("(",F28)-1),F28),Tipos!$A:$B,2,FALSE()),"outro") -> uuid | M28: =IF(COUNTIF(Comparação!$H:$H,A28)>0,"sim",IF(AND(G28="sim",H28=""),"FALTA (obrigatória)","não")) -> FALTA (obrigatória)
A29: =B29&"."&E29 -> anuncios.campanha_canal_id | B29: anuncios | C29: Marketing e campanhas | D29: 3 | E29: campanha_canal_id | F29: uuid | G29: sim | I29: UNIQUE | J29: campanha_canais.id | L29: =IFERROR(VLOOKUP(IF(ISNUMBER(SEARCH("(",F29)),LEFT(F29,SEARCH("(",F29)-1),F29),Tipos!$A:$B,2,FALSE()),"outro") -> uuid | M29: =IF(COUNTIF(Comparação!$H:$H,A29)>0,"sim",IF(AND(G29="sim",H29=""),"FALTA (obrigatória)","não")) -> FALTA (obrigatória)
A30: =B30&"."&E30 -> anuncios.nome | B30: anuncios | C30: Marketing e campanhas | D30: 4 | E30: nome | F30: text | G30: sim | L30: =IFERROR(VLOOKUP(IF(ISNUMBER(SEARCH("(",F30)),LEFT(F30,SEARCH("(",F30)-1),F30),Tipos!$A:$B,2,FALSE()),"outro") -> texto | M30: =IF(COUNTIF(Comparação!$H:$H,A30)>0,"sim",IF(AND(G30="sim",H30=""),"FALTA (obrigatória)","não")) -> FALTA (obrigatória)
A31: =B31&"."&E31 -> anuncios.utm_content | B31: anuncios | C31: Marketing e campanhas | D31: 5 | E31: utm_content | F31: text | G31: sim | I31: UNIQUE | L31: =IFERROR(VLOOKUP(IF(ISNUMBER(SEARCH("(",F31)),LEFT(F31,SEARCH("(",F31)-1),F31),Tipos!$A:$B,2,FALSE()),"outro") -> texto | M31: =IF(COUNTIF(Comparação!$H:$H,A31)>0,"sim",IF(AND(G31="sim",H31=""),"FALTA (obrigatória)","não")) -> FALTA (obrigatória)
A32: =B32&"."&E32 -> anuncios.imagem_url | B32: anuncios | C32: Marketing e campanhas | D32: 6 | E32: imagem_url | F32: text | G32: não | L32: =IFERROR(VLOOKUP(IF(ISNUMBER(SEARCH("(",F32)),LEFT(F32,SEARCH("(",F32)-1),F32),Tipos!$A:$B,2,FALSE()),"outro") -> texto | M32: =IF(COUNTIF(Comparação!$H:$H,A32)>0,"sim",IF(AND(G32="sim",H32=""),"FALTA (obrigatória)","não")) -> não
A33: =B33&"."&E33 -> anuncios.id_externo | B33: anuncios | C33: Marketing e campanhas | D33: 7 | E33: id_externo | F33: text | G33: não | L33: =IFERROR(VLOOKUP(IF(ISNUMBER(SEARCH("(",F33)),LEFT(F33,SEARCH("(",F33)-1),F33),Tipos!$A:$B,2,FALSE()),"outro") -> texto | M33: =IF(COUNTIF(Comparação!$H:$H,A33)>0,"sim",IF(AND(G33="sim",H33=""),"FALTA (obrigatória)","não")) -> não
A34: =B34&"."&E34 -> anuncios.ativo | B34: anuncios | C34: Marketing e campanhas | D34: 8 | E34: ativo | F34: boolean | G34: sim | H34: true | L34: =IFERROR(VLOOKUP(IF(ISNUMBER(SEARCH("(",F34)),LEFT(F34,SEARCH("(",F34)-1),F34),Tipos!$A:$B,2,FALSE()),"outro") -> booleano | M34: =IF(COUNTIF(Comparação!$H:$H,A34)>0,"sim",IF(AND(G34="sim",H34=""),"FALTA (obrigatória)","não")) -> não
A35: =B35&"."&E35 -> anuncios.angulo | B35: anuncios | C35: Marketing e campanhas | D35: 9 | E35: angulo | F35: text | G35: não | L35: =IFERROR(VLOOKUP(IF(ISNUMBER(SEARCH("(",F35)),LEFT(F35,SEARCH("(",F35)-1),F35),Tipos!$A:$B,2,FALSE()),"outro") -> texto | M35: =IF(COUNTIF(Comparação!$H:$H,A35)>0,"sim",IF(AND(G35="sim",H35=""),"FALTA (obrigatória)","não")) -> não
A36: =B36&"."&E36 -> anuncios.temperatura | B36: anuncios | C36: Marketing e campanhas | D36: 10 | E36: temperatura | F36: text | G36: não | K36: CHECK (((temperatura IS NULL) OR (temperatura = ANY (ARRAY['frio'::text, 'quente'::text])))) | L36: =IFERROR(VLOOKUP(IF(ISNUMBER(SEARCH("(",F36)),LEFT(F36,SEARCH("(",F36)-1),F36),Tipos!$A:$B,2,FALSE()),"outro") -> texto | M36: =IF(COUNTIF(Comparação!$H:$H,A36)>0,"sim",IF(AND(G36="sim",H36=""),"FALTA (obrigatória)","não")) -> não
A37: =B37&"."&E37 -> auditoria.id | B37: auditoria | C37: Sistema | D37: 1 | E37: id | F37: bigint | G37: sim | H37: nextval('auditoria_id_seq'::regclass) | I37: PRIMARY KEY | L37: =IFERROR(VLOOKUP(IF(ISNUMBER(SEARCH("(",F37)),LEFT(F37,SEARCH("(",F37)-1),F37),Tipos!$A:$B,2,FALSE()),"outro") -> inteiro | M37: =IF(COUNTIF(Comparação!$H:$H,A37)>0,"sim",IF(AND(G37="sim",H37=""),"FALTA (obrigatória)","não")) -> não
A38: =B38&"."&E38 -> auditoria.workspace_id | B38: auditoria | C38: Sistema | D38: 2 | E38: workspace_id | F38: uuid | G38: não | L38: =IFERROR(VLOOKUP(IF(ISNUMBER(SEARCH("(",F38)),LEFT(F38,SEARCH("(",F38)-1),F38),Tipos!$A:$B,2,FALSE()),"outro") -> uuid | M38: =IF(COUNTIF(Comparação!$H:$H,A38)>0,"sim",IF(AND(G38="sim",H38=""),"FALTA (obrigatória)","não")) -> não
A39: =B39&"."&E39 -> auditoria.tabela | B39: auditoria | C39: Sistema | D39: 3 | E39: tabela | F39: text | G39: sim | L39: =IFERROR(VLOOKUP(IF(ISNUMBER(SEARCH("(",F39)),LEFT(F39,SEARCH("(",F39)-1),F39),Tipos!$A:$B,2,FALSE()),"outro") -> texto | M39: =IF(COUNTIF(Comparação!$H:$H,A39)>0,"sim",IF(AND(G39="sim",H39=""),"FALTA (obrigatória)","não")) -> FALTA (obrigatória)
A40: =B40&"."&E40 -> auditoria.registro_id | B40: auditoria | C40: Sistema | D40: 4 | E40: registro_id | F40: uuid | G40: não | L40: =IFERROR(VLOOKUP(IF(ISNUMBER(SEARCH("(",F40)),LEFT(F40,SEARCH("(",F40)-1),F40),Tipos!$A:$B,2,FALSE()),"outro") -> uuid | M40: =IF(COUNTIF(Comparação!$H:$H,A40)>0,"sim",IF(AND(G40="sim",H40=""),"FALTA (obrigatória)","não")) -> não
A41: =B41&"."&E41 -> auditoria.acao | B41: auditoria | C41: Sistema | D41: 5 | E41: acao | F41: text | G41: sim | K41: CHECK ((acao = ANY (ARRAY['inclusao'::text, 'alteracao'::text, 'exclusao'::text]))) | L41: =IFERROR(VLOOKUP(IF(ISNUMBER(SEARCH("(",F41)),LEFT(F41,SEARCH("(",F41)-1),F41),Tipos!$A:$B,2,FALSE()),"outro") -> texto | M41: =IF(COUNTIF(Comparação!$H:$H,A41)>0,"sim",IF(AND(G41="sim",H41=""),"FALTA (obrigatória)","não")) -> FALTA (obrigatória)
A42: =B42&"."&E42 -> auditoria.campos | B42: auditoria | C42: Sistema | D42: 6 | E42: campos | F42: _text | G42: não | L42: =IFERROR(VLOOKUP(IF(ISNUMBER(SEARCH("(",F42)),LEFT(F42,SEARCH("(",F42)-1),F42),Tipos!$A:$B,2,FALSE()),"outro") -> lista | M42: =IF(COUNTIF(Comparação!$H:$H,A42)>0,"sim",IF(AND(G42="sim",H42=""),"FALTA (obrigatória)","não")) -> não
A43: =B43&"."&E43 -> auditoria.antes | B43: auditoria | C43: Sistema | D43: 7 | E43: antes | F43: jsonb | G43: não | L43: =IFERROR(VLOOKUP(IF(ISNUMBER(SEARCH("(",F43)),LEFT(F43,SEARCH("(",F43)-1),F43),Tipos!$A:$B,2,FALSE()),"outro") -> json | M43: =IF(COUNTIF(Comparação!$H:$H,A43)>0,"sim",IF(AND(G43="sim",H43=""),"FALTA (obrigatória)","não")) -> não
A44: =B44&"."&E44 -> auditoria.depois | B44: auditoria | C44: Sistema | D44: 8 | E44: depois | F44: jsonb | G44: não | L44: =IFERROR(VLOOKUP(IF(ISNUMBER(SEARCH("(",F44)),LEFT(F44,SEARCH("(",F44)-1),F44),Tipos!$A:$B,2,FALSE()),"outro") -> json | M44: =IF(COUNTIF(Comparação!$H:$H,A44)>0,"sim",IF(AND(G44="sim",H44=""),"FALTA (obrigatória)","não")) -> não
A45: =B45&"."&E45 -> auditoria.usuario_id | B45: auditoria | C45: Sistema | D45: 9 | E45: usuario_id | F45: uuid | G45: não | L45: =IFERROR(VLOOKUP(IF(ISNUMBER(SEARCH("(",F45)),LEFT(F45,SEARCH("(",F45)-1),F45),Tipos!$A:$B,2,FALSE()),"outro") -> uuid | M45: =IF(COUNTIF(Comparação!$H:$H,A45)>0,"sim",IF(AND(G45="sim",H45=""),"FALTA (obrigatória)","não")) -> não
A46: =B46&"."&E46 -> auditoria.usuario_email | B46: auditoria | C46: Sistema | D46: 10 | E46: usuario_email | F46: text | G46: não | L46: =IFERROR(VLOOKUP(IF(ISNUMBER(SEARCH("(",F46)),LEFT(F46,SEARCH("(",F46)-1),F46),Tipos!$A:$B,2,FALSE()),"outro") -> texto | M46: =IF(COUNTIF(Comparação!$H:$H,A46)>0,"sim",IF(AND(G46="sim",H46=""),"FALTA (obrigatória)","não")) -> não
A47: =B47&"."&E47 -> auditoria.origem | B47: auditoria | C47: Sistema | D47: 11 | E47: origem | F47: text | G47: sim | L47: =IFERROR(VLOOKUP(IF(ISNUMBER(SEARCH("(",F47)),LEFT(F47,SEARCH("(",F47)-1),F47),Tipos!$A:$B,2,FALSE()),"outro") -> texto | M47: =IF(COUNTIF(Comparação!$H:$H,A47)>0,"sim",IF(AND(G47="sim",H47=""),"FALTA (obrigatória)","não")) -> FALTA (obrigatória)
A48: =B48&"."&E48 -> auditoria.em | B48: auditoria | C48: Sistema | D48: 12 | E48: em | F48: timestamptz | G48: sim | H48: now() | L48: =IFERROR(VLOOKUP(IF(ISNUMBER(SEARCH("(",F48)),LEFT(F48,SEARCH("(",F48)-1),F48),Tipos!$A:$B,2,FALSE()),"outro") -> data e hora | M48: =IF(COUNTIF(Comparação!$H:$H,A48)>0,"sim",IF(AND(G48="sim",H48=""),"FALTA (obrigatória)","não")) -> não
A49: =B49&"."&E49 -> benchmarks_mercado.id | B49: benchmarks_mercado | C49: Planejamento | D49: 1 | E49: id | F49: uuid | G49: sim | H49: gen_random_uuid() | I49: PRIMARY KEY | L49: =IFERROR(VLOOKUP(IF(ISNUMBER(SEARCH("(",F49)),LEFT(F49,SEARCH("(",F49)-1),F49),Tipos!$A:$B,2,FALSE()),"outro") -> uuid | M49: =IF(COUNTIF(Comparação!$H:$H,A49)>0,"sim",IF(AND(G49="sim",H49=""),"FALTA (obrigatória)","não")) -> não
A50: =B50&"."&E50 -> benchmarks_mercado.workspace_id | B50: benchmarks_mercado | C50: Planejamento | D50: 2 | E50: workspace_id | F50: uuid | G50: sim | I50: UNIQUE | J50: workspaces.id | L50: =IFERROR(VLOOKUP(IF(ISNUMBER(SEARCH("(",F50)),LEFT(F50,SEARCH("(",F50)-1),F50),Tipos!$A:$B,2,FALSE()),"outro") -> uuid | M50: =IF(COUNTIF(Comparação!$H:$H,A50)>0,"sim",IF(AND(G50="sim",H50=""),"FALTA (obrigatória)","não")) -> FALTA (obrigatória)
A51: =B51&"."&E51 -> benchmarks_mercado.metrica | B51: benchmarks_mercado | C51: Planejamento | D51: 3 | E51: metrica | F51: text | G51: sim | I51: UNIQUE | K51: CHECK ((metrica = ANY (ARRAY['cpl'::text, 'cac'::text, 'conv'::text, 'ticket'::text, 'roas'::text, 'margem'::text, 'leads'::text, 'receita'::text]))) | L51: =IFERROR(VLOOKUP(IF(ISNUMBER(SEARCH("(",F51)),LEFT(F51,SEARCH("(",F51)-1),F51),Tipos!$A:$B,2,FALSE()),"outro") -> texto | M51: =IF(COUNTIF(Comparação!$H:$H,A51)>0,"sim",IF(AND(G51="sim",H51=""),"FALTA (obrigatória)","não")) -> FALTA (obrigatória)
A52: =B52&"."&E52 -> benchmarks_mercado.valor | B52: benchmarks_mercado | C52: Planejamento | D52: 4 | E52: valor | F52: numeric(14,4) | G52: sim | K52: CHECK ((valor >= (0)::numeric)) | L52: =IFERROR(VLOOKUP(IF(ISNUMBER(SEARCH("(",F52)),LEFT(F52,SEARCH("(",F52)-1),F52),Tipos!$A:$B,2,FALSE()),"outro") -> decimal | M52: =IF(COUNTIF(Comparação!$H:$H,A52)>0,"sim",IF(AND(G52="sim",H52=""),"FALTA (obrigatória)","não")) -> FALTA (obrigatória)
A53: =B53&"."&E53 -> benchmarks_mercado.fonte | B53: benchmarks_mercado | C53: Planejamento | D53: 5 | E53: fonte | F53: text | G53: não | K53: CHECK (((fonte IS NULL) OR (char_length(fonte) <= 200))) | L53: =IFERROR(VLOOKUP(IF(ISNUMBER(SEARCH("(",F53)),LEFT(F53,SEARCH("(",F53)-1),F53),Tipos!$A:$B,2,FALSE()),"outro") -> texto | M53: =IF(COUNTIF(Comparação!$H:$H,A53)>0,"sim",IF(AND(G53="sim",H53=""),"FALTA (obrigatória)","não")) -> não
A54: =B54&"."&E54 -> benchmarks_mercado.atualizado_em | B54: benchmarks_mercado | C54: Planejamento | D54: 6 | E54: atualizado_em | F54: timestamptz | G54: sim | H54: now() | L54: =IFERROR(VLOOKUP(IF(ISNUMBER(SEARCH("(",F54)),LEFT(F54,SEARCH("(",F54)-1),F54),Tipos!$A:$B,2,FALSE()),"outro") -> data e hora | M54: =IF(COUNTIF(Comparação!$H:$H,A54)>0,"sim",IF(AND(G54="sim",H54=""),"FALTA (obrigatória)","não")) -> não
A55: =B55&"."&E55 -> campanha_blocos.id | B55: campanha_blocos | C55: Marketing e campanhas | D55: 1 | E55: id | F55: uuid | G55: sim | H55: gen_random_uuid() | I55: PRIMARY KEY | L55: =IFERROR(VLOOKUP(IF(ISNUMBER(SEARCH("(",F55)),LEFT(F55,SEARCH("(",F55)-1),F55),Tipos!$A:$B,2,FALSE()),"outro") -> uuid | M55: =IF(COUNTIF(Comparação!$H:$H,A55)>0,"sim",IF(AND(G55="sim",H55=""),"FALTA (obrigatória)","não")) -> não
A56: =B56&"."&E56 -> campanha_blocos.workspace_id | B56: campanha_blocos | C56: Marketing e campanhas | D56: 2 | E56: workspace_id | F56: uuid | G56: sim | J56: workspaces.id | L56: =IFERROR(VLOOKUP(IF(ISNUMBER(SEARCH("(",F56)),LEFT(F56,SEARCH("(",F56)-1),F56),Tipos!$A:$B,2,FALSE()),"outro") -> uuid | M56: =IF(COUNTIF(Comparação!$H:$H,A56)>0,"sim",IF(AND(G56="sim",H56=""),"FALTA (obrigatória)","não")) -> FALTA (obrigatória)
A57: =B57&"."&E57 -> campanha_blocos.campanha_id | B57: campanha_blocos | C57: Marketing e campanhas | D57: 3 | E57: campanha_id | F57: uuid | G57: sim | J57: campanhas.id | L57: =IFERROR(VLOOKUP(IF(ISNUMBER(SEARCH("(",F57)),LEFT(F57,SEARCH("(",F57)-1),F57),Tipos!$A:$B,2,FALSE()),"outro") -> uuid | M57: =IF(COUNTIF(Comparação!$H:$H,A57)>0,"sim",IF(AND(G57="sim",H57=""),"FALTA (obrigatória)","não")) -> FALTA (obrigatória)
A58: =B58&"."&E58 -> campanha_blocos.bloco_origem_id | B58: campanha_blocos | C58: Marketing e campanhas | D58: 4 | E58: bloco_origem_id | F58: uuid | G58: não | L58: =IFERROR(VLOOKUP(IF(ISNUMBER(SEARCH("(",F58)),LEFT(F58,SEARCH("(",F58)-1),F58),Tipos!$A:$B,2,FALSE()),"outro") -> uuid | M58: =IF(COUNTIF(Comparação!$H:$H,A58)>0,"sim",IF(AND(G58="sim",H58=""),"FALTA (obrigatória)","não")) -> não
A59: =B59&"."&E59 -> campanha_blocos.ordem | B59: campanha_blocos | C59: Marketing e campanhas | D59: 5 | E59: ordem | F59: integer | G59: sim | H59: 10 | L59: =IFERROR(VLOOKUP(IF(ISNUMBER(SEARCH("(",F59)),LEFT(F59,SEARCH("(",F59)-1),F59),Tipos!$A:$B,2,FALSE()),"outro") -> inteiro | M59: =IF(COUNTIF(Comparação!$H:$H,A59)>0,"sim",IF(AND(G59="sim",H59=""),"FALTA (obrigatória)","não")) -> não
A60: =B60&"."&E60 -> campanha_blocos.fase | B60: campanha_blocos | C60: Marketing e campanhas | D60: 6 | E60: fase | F60: text | G60: sim | H60: 'aquisicao'::text | K60: CHECK ((fase = ANY (ARRAY['aquisicao'::text, 'aquecimento'::text, 'conversao'::text, 'retencao'::text]))) | L60: =IFERROR(VLOOKUP(IF(ISNUMBER(SEARCH("(",F60)),LEFT(F60,SEARCH("(",F60)-1),F60),Tipos!$A:$B,2,FALSE()),"outro") -> texto | M60: =IF(COUNTIF(Comparação!$H:$H,A60)>0,"sim",IF(AND(G60="sim",H60=""),"FALTA (obrigatória)","não")) -> não
A61: =B61&"."&E61 -> campanha_blocos.tipo | B61: campanha_blocos | C61: Marketing e campanhas | D61: 7 | E61: tipo | F61: text | G61: sim | L61: =IFERROR(VLOOKUP(IF(ISNUMBER(SEARCH("(",F61)),LEFT(F61,SEARCH("(",F61)-1),F61),Tipos!$A:$B,2,FALSE()),"outro") -> texto | M61: =IF(COUNTIF(Comparação!$H:$H,A61)>0,"sim",IF(AND(G61="sim",H61=""),"FALTA (obrigatória)","não")) -> FALTA (obrigatória)
A62: =B62&"."&E62 -> campanha_blocos.nome | B62: campanha_blocos | C62: Marketing e campanhas | D62: 8 | E62: nome | F62: text | G62: sim | L62: =IFERROR(VLOOKUP(IF(ISNUMBER(SEARCH("(",F62)),LEFT(F62,SEARCH("(",F62)-1),F62),Tipos!$A:$B,2,FALSE()),"outro") -> texto | M62: =IF(COUNTIF(Comparação!$H:$H,A62)>0,"sim",IF(AND(G62="sim",H62=""),"FALTA (obrigatória)","não")) -> FALTA (obrigatória)
A63: =B63&"."&E63 -> campanha_blocos.origem_ref | B63: campanha_blocos | C63: Marketing e campanhas | D63: 9 | E63: origem_ref | F63: uuid | G63: não | L63: =IFERROR(VLOOKUP(IF(ISNUMBER(SEARCH("(",F63)),LEFT(F63,SEARCH("(",F63)-1),F63),Tipos!$A:$B,2,FALSE()),"outro") -> uuid | M63: =IF(COUNTIF(Comparação!$H:$H,A63)>0,"sim",IF(AND(G63="sim",H63=""),"FALTA (obrigatória)","não")) -> não
A64: =B64&"."&E64 -> campanha_blocos.ativo | B64: campanha_blocos | C64: Marketing e campanhas | D64: 10 | E64: ativo | F64: boolean | G64: sim | H64: true | L64: =IFERROR(VLOOKUP(IF(ISNUMBER(SEARCH("(",F64)),LEFT(F64,SEARCH("(",F64)-1),F64),Tipos!$A:$B,2,FALSE()),"outro") -> booleano | M64: =IF(COUNTIF(Comparação!$H:$H,A64)>0,"sim",IF(AND(G64="sim",H64=""),"FALTA (obrigatória)","não")) -> não
A65: =B65&"."&E65 -> campanha_blocos.criado_em | B65: campanha_blocos | C65: Marketing e campanhas | D65: 11 | E65: criado_em | F65: timestamptz | G65: sim | H65: now() | L65: =IFERROR(VLOOKUP(IF(ISNUMBER(SEARCH("(",F65)),LEFT(F65,SEARCH("(",F65)-1),F65),Tipos!$A:$B,2,FALSE()),"outro") -> data e hora | M65: =IF(COUNTIF(Comparação!$H:$H,A65)>0,"sim",IF(AND(G65="sim",H65=""),"FALTA (obrigatória)","não")) -> não
A66: =B66&"."&E66 -> campanha_calculos.id | B66: campanha_calculos | C66: Marketing e campanhas | D66: 1 | E66: id | F66: uuid | G66: sim | H66: gen_random_uuid() | I66: PRIMARY KEY | L66: =IFERROR(VLOOKUP(IF(ISNUMBER(SEARCH("(",F66)),LEFT(F66,SEARCH("(",F66)-1),F66),Tipos!$A:$B,2,FALSE()),"outro") -> uuid | M66: =IF(COUNTIF(Comparação!$H:$H,A66)>0,"sim",IF(AND(G66="sim",H66=""),"FALTA (obrigatória)","não")) -> não
A67: =B67&"."&E67 -> campanha_calculos.workspace_id | B67: campanha_calculos | C67: Marketing e campanhas | D67: 2 | E67: workspace_id | F67: uuid | G67: sim | J67: workspaces.id | L67: =IFERROR(VLOOKUP(IF(ISNUMBER(SEARCH("(",F67)),LEFT(F67,SEARCH("(",F67)-1),F67),Tipos!$A:$B,2,FALSE()),"outro") -> uuid | M67: =IF(COUNTIF(Comparação!$H:$H,A67)>0,"sim",IF(AND(G67="sim",H67=""),"FALTA (obrigatória)","não")) -> FALTA (obrigatória)
A68: =B68&"."&E68 -> campanha_calculos.campanha_id | B68: campanha_calculos | C68: Marketing e campanhas | D68: 3 | E68: campanha_id | F68: uuid | G68: não | J68: campanhas.id | L68: =IFERROR(VLOOKUP(IF(ISNUMBER(SEARCH("(",F68)),LEFT(F68,SEARCH("(",F68)-1),F68),Tipos!$A:$B,2,FALSE()),"outro") -> uuid | M68: =IF(COUNTIF(Comparação!$H:$H,A68)>0,"sim",IF(AND(G68="sim",H68=""),"FALTA (obrigatória)","não")) -> não
A69: =B69&"."&E69 -> campanha_calculos.nome | B69: campanha_calculos | C69: Marketing e campanhas | D69: 4 | E69: nome | F69: text | G69: sim | K69: CHECK (((char_length(nome) >= 1) AND (char_length(nome) <= 120))) | L69: =IFERROR(VLOOKUP(IF(ISNUMBER(SEARCH("(",F69)),LEFT(F69,SEARCH("(",F69)-1),F69),Tipos!$A:$B,2,FALSE()),"outro") -> texto | M69: =IF(COUNTIF(Comparação!$H:$H,A69)>0,"sim",IF(AND(G69="sim",H69=""),"FALTA (obrigatória)","não")) -> FALTA (obrigatória)
A70: =B70&"."&E70 -> campanha_calculos.premissas | B70: campanha_calculos | C70: Marketing e campanhas | D70: 5 | E70: premissas | F70: jsonb | G70: sim | H70: '{}'::jsonb | K70: CHECK ((jsonb_typeof(premissas) = 'object'::text)) | L70: =IFERROR(VLOOKUP(IF(ISNUMBER(SEARCH("(",F70)),LEFT(F70,SEARCH("(",F70)-1),F70),Tipos!$A:$B,2,FALSE()),"outro") -> json | M70: =IF(COUNTIF(Comparação!$H:$H,A70)>0,"sim",IF(AND(G70="sim",H70=""),"FALTA (obrigatória)","não")) -> não
A71: =B71&"."&E71 -> campanha_calculos.criado_em | B71: campanha_calculos | C71: Marketing e campanhas | D71: 6 | E71: criado_em | F71: timestamptz | G71: sim | H71: now() | L71: =IFERROR(VLOOKUP(IF(ISNUMBER(SEARCH("(",F71)),LEFT(F71,SEARCH("(",F71)-1),F71),Tipos!$A:$B,2,FALSE()),"outro") -> data e hora | M71: =IF(COUNTIF(Comparação!$H:$H,A71)>0,"sim",IF(AND(G71="sim",H71=""),"FALTA (obrigatória)","não")) -> não
A72: =B72&"."&E72 -> campanha_calculos.atualizado_em | B72: campanha_calculos | C72: Marketing e campanhas | D72: 7 | E72: atualizado_em | F72: timestamptz | G72: sim | H72: now() | L72: =IFERROR(VLOOKUP(IF(ISNUMBER(SEARCH("(",F72)),LEFT(F72,SEARCH("(",F72)-1),F72),Tipos!$A:$B,2,FALSE()),"outro") -> data e hora | M72: =IF(COUNTIF(Comparação!$H:$H,A72)>0,"sim",IF(AND(G72="sim",H72=""),"FALTA (obrigatória)","não")) -> não
A73: =B73&"."&E73 -> campanha_canais.id | B73: campanha_canais | C73: Marketing e campanhas | D73: 1 | E73: id | F73: uuid | G73: sim | H73: gen_random_uuid() | I73: PRIMARY KEY | L73: =IFERROR(VLOOKUP(IF(ISNUMBER(SEARCH("(",F73)),LEFT(F73,SEARCH("(",F73)-1),F73),Tipos!$A:$B,2,FALSE()),"outro") -> uuid | M73: =IF(COUNTIF(Comparação!$H:$H,A73)>0,"sim",IF(AND(G73="sim",H73=""),"FALTA (obrigatória)","não")) -> não
A74: =B74&"."&E74 -> campanha_canais.workspace_id | B74: campanha_canais | C74: Marketing e campanhas | D74: 2 | E74: workspace_id | F74: uuid | G74: sim | I74: UNIQUE | J74: workspaces.id, canais.workspace_id | L74: =IFERROR(VLOOKUP(IF(ISNUMBER(SEARCH("(",F74)),LEFT(F74,SEARCH("(",F74)-1),F74),Tipos!$A:$B,2,FALSE()),"outro") -> uuid | M74: =IF(COUNTIF(Comparação!$H:$H,A74)>0,"sim",IF(AND(G74="sim",H74=""),"FALTA (obrigatória)","não")) -> FALTA (obrigatória)
A75: =B75&"."&E75 -> campanha_canais.campanha_id | B75: campanha_canais | C75: Marketing e campanhas | D75: 3 | E75: campanha_id | F75: uuid | G75: sim | J75: campanhas.id | L75: =IFERROR(VLOOKUP(IF(ISNUMBER(SEARCH("(",F75)),LEFT(F75,SEARCH("(",F75)-1),F75),Tipos!$A:$B,2,FALSE()),"outro") -> uuid | M75: =IF(COUNTIF(Comparação!$H:$H,A75)>0,"sim",IF(AND(G75="sim",H75=""),"FALTA (obrigatória)","não")) -> FALTA (obrigatória)
A76: =B76&"."&E76 -> campanha_canais.canal | B76: campanha_canais | C76: Marketing e campanhas | D76: 4 | E76: canal | F76: text | G76: sim | J76: canais.codigo | L76: =IFERROR(VLOOKUP(IF(ISNUMBER(SEARCH("(",F76)),LEFT(F76,SEARCH("(",F76)-1),F76),Tipos!$A:$B,2,FALSE()),"outro") -> texto | M76: =IF(COUNTIF(Comparação!$H:$H,A76)>0,"sim",IF(AND(G76="sim",H76=""),"FALTA (obrigatória)","não")) -> FALTA (obrigatória)
A77: =B77&"."&E77 -> campanha_canais.utm_campaign | B77: campanha_canais | C77: Marketing e campanhas | D77: 5 | E77: utm_campaign | F77: text | G77: sim | I77: UNIQUE | L77: =IFERROR(VLOOKUP(IF(ISNUMBER(SEARCH("(",F77)),LEFT(F77,SEARCH("(",F77)-1),F77),Tipos!$A:$B,2,FALSE()),"outro") -> texto | M77: =IF(COUNTIF(Comparação!$H:$H,A77)>0,"sim",IF(AND(G77="sim",H77=""),"FALTA (obrigatória)","não")) -> FALTA (obrigatória)
A78: =B78&"."&E78 -> campanha_canais.orcamento | B78: campanha_canais | C78: Marketing e campanhas | D78: 6 | E78: orcamento | F78: numeric(14,2) | G78: não | L78: =IFERROR(VLOOKUP(IF(ISNUMBER(SEARCH("(",F78)),LEFT(F78,SEARCH("(",F78)-1),F78),Tipos!$A:$B,2,FALSE()),"outro") -> decimal | M78: =IF(COUNTIF(Comparação!$H:$H,A78)>0,"sim",IF(AND(G78="sim",H78=""),"FALTA (obrigatória)","não")) -> não
A79: =B79&"."&E79 -> campanha_canais.percentual_meta_leads | B79: campanha_canais | C79: Marketing e campanhas | D79: 7 | E79: percentual_meta_leads | F79: numeric(6,3) | G79: não | L79: =IFERROR(VLOOKUP(IF(ISNUMBER(SEARCH("(",F79)),LEFT(F79,SEARCH("(",F79)-1),F79),Tipos!$A:$B,2,FALSE()),"outro") -> decimal | M79: =IF(COUNTIF(Comparação!$H:$H,A79)>0,"sim",IF(AND(G79="sim",H79=""),"FALTA (obrigatória)","não")) -> não
A80: =B80&"."&E80 -> campanha_canais.meta_leads | B80: campanha_canais | C80: Marketing e campanhas | D80: 8 | E80: meta_leads | F80: integer | G80: não | L80: =IFERROR(VLOOKUP(IF(ISNUMBER(SEARCH("(",F80)),LEFT(F80,SEARCH("(",F80)-1),F80),Tipos!$A:$B,2,FALSE()),"outro") -> inteiro | M80: =IF(COUNTIF(Comparação!$H:$H,A80)>0,"sim",IF(AND(G80="sim",H80=""),"FALTA (obrigatória)","não")) -> não
A81: =B81&"."&E81 -> campanha_canais.meta_vendas | B81: campanha_canais | C81: Marketing e campanhas | D81: 9 | E81: meta_vendas | F81: integer | G81: não | L81: =IFERROR(VLOOKUP(IF(ISNUMBER(SEARCH("(",F81)),LEFT(F81,SEARCH("(",F81)-1),F81),Tipos!$A:$B,2,FALSE()),"outro") -> inteiro | M81: =IF(COUNTIF(Comparação!$H:$H,A81)>0,"sim",IF(AND(G81="sim",H81=""),"FALTA (obrigatória)","não")) -> não
A82: =B82&"."&E82 -> campanha_canais.meta_cac | B82: campanha_canais | C82: Marketing e campanhas | D82: 10 | E82: meta_cac | F82: numeric(12,2) | G82: não | L82: =IFERROR(VLOOKUP(IF(ISNUMBER(SEARCH("(",F82)),LEFT(F82,SEARCH("(",F82)-1),F82),Tipos!$A:$B,2,FALSE()),"outro") -> decimal | M82: =IF(COUNTIF(Comparação!$H:$H,A82)>0,"sim",IF(AND(G82="sim",H82=""),"FALTA (obrigatória)","não")) -> não
A83: =B83&"."&E83 -> campanha_canais.meta_cpl | B83: campanha_canais | C83: Marketing e campanhas | D83: 11 | E83: meta_cpl | F83: numeric(12,2) | G83: não | K83: CHECK (((meta_cpl IS NULL) OR (meta_cpl >= (0)::numeric))) | L83: =IFERROR(VLOOKUP(IF(ISNUMBER(SEARCH("(",F83)),LEFT(F83,SEARCH("(",F83)-1),F83),Tipos!$A:$B,2,FALSE()),"outro") -> decimal | M83: =IF(COUNTIF(Comparação!$H:$H,A83)>0,"sim",IF(AND(G83="sim",H83=""),"FALTA (obrigatória)","não")) -> não
A84: =B84&"."&E84 -> campanha_canais.temperatura | B84: campanha_canais | C84: Marketing e campanhas | D84: 12 | E84: temperatura | F84: text | G84: não | K84: CHECK (((temperatura IS NULL) OR (temperatura = ANY (ARRAY['frio'::text, 'quente'::text])))) | L84: =IFERROR(VLOOKUP(IF(ISNUMBER(SEARCH("(",F84)),LEFT(F84,SEARCH("(",F84)-1),F84),Tipos!$A:$B,2,FALSE()),"outro") -> texto | M84: =IF(COUNTIF(Comparação!$H:$H,A84)>0,"sim",IF(AND(G84="sim",H84=""),"FALTA (obrigatória)","não")) -> não
A85: =B85&"."&E85 -> campanha_canais.tipo | B85: campanha_canais | C85: Marketing e campanhas | D85: 13 | E85: tipo | F85: text | G85: não | K85: CHECK (((tipo IS NULL) OR (tipo = ANY (ARRAY['pago'::text, 'organico'::text])))) | L85: =IFERROR(VLOOKUP(IF(ISNUMBER(SEARCH("(",F85)),LEFT(F85,SEARCH("(",F85)-1),F85),Tipos!$A:$B,2,FALSE()),"outro") -> texto | M85: =IF(COUNTIF(Comparação!$H:$H,A85)>0,"sim",IF(AND(G85="sim",H85=""),"FALTA (obrigatória)","não")) -> não
A86: =B86&"."&E86 -> campanha_canais.funil_id | B86: campanha_canais | C86: Marketing e campanhas | D86: 14 | E86: funil_id | F86: uuid | G86: não | J86: funis.id | L86: =IFERROR(VLOOKUP(IF(ISNUMBER(SEARCH("(",F86)),LEFT(F86,SEARCH("(",F86)-1),F86),Tipos!$A:$B,2,FALSE()),"outro") -> uuid | M86: =IF(COUNTIF(Comparação!$H:$H,A86)>0,"sim",IF(AND(G86="sim",H86=""),"FALTA (obrigatória)","não")) -> não
A87: =B87&"."&E87 -> campanha_canais.custo_producao | B87: campanha_canais | C87: Marketing e campanhas | D87: 15 | E87: custo_producao | F87: numeric(12,2) | G87: não | K87: CHECK (((custo_producao IS NULL) OR (custo_producao >= (0)::numeric))) | L87: =IFERROR(VLOOKUP(IF(ISNUMBER(SEARCH("(",F87)),LEFT(F87,SEARCH("(",F87)-1),F87),Tipos!$A:$B,2,FALSE()),"outro") -> decimal | M87: =IF(COUNTIF(Comparação!$H:$H,A87)>0,"sim",IF(AND(G87="sim",H87=""),"FALTA (obrigatória)","não")) -> não
A88: =B88&"."&E88 -> campanha_canais.observacoes | B88: campanha_canais | C88: Marketing e campanhas | D88: 16 | E88: observacoes | F88: text | G88: não | L88: =IFERROR(VLOOKUP(IF(ISNUMBER(SEARCH("(",F88)),LEFT(F88,SEARCH("(",F88)-1),F88),Tipos!$A:$B,2,FALSE()),"outro") -> texto | M88: =IF(COUNTIF(Comparação!$H:$H,A88)>0,"sim",IF(AND(G88="sim",H88=""),"FALTA (obrigatória)","não")) -> não
A89: =B89&"."&E89 -> campanha_debriefing.id | B89: campanha_debriefing | C89: Marketing e campanhas | D89: 1 | E89: id | F89: uuid | G89: sim | H89: gen_random_uuid() | I89: PRIMARY KEY | L89: =IFERROR(VLOOKUP(IF(ISNUMBER(SEARCH("(",F89)),LEFT(F89,SEARCH("(",F89)-1),F89),Tipos!$A:$B,2,FALSE()),"outro") -> uuid | M89: =IF(COUNTIF(Comparação!$H:$H,A89)>0,"sim",IF(AND(G89="sim",H89=""),"FALTA (obrigatória)","não")) -> não
A90: =B90&"."&E90 -> campanha_debriefing.workspace_id | B90: campanha_debriefing | C90: Marketing e campanhas | D90: 2 | E90: workspace_id | F90: uuid | G90: sim | J90: workspaces.id | L90: =IFERROR(VLOOKUP(IF(ISNUMBER(SEARCH("(",F90)),LEFT(F90,SEARCH("(",F90)-1),F90),Tipos!$A:$B,2,FALSE()),"outro") -> uuid | M90: =IF(COUNTIF(Comparação!$H:$H,A90)>0,"sim",IF(AND(G90="sim",H90=""),"FALTA (obrigatória)","não")) -> FALTA (obrigatória)
A91: =B91&"."&E91 -> campanha_debriefing.campanha_id | B91: campanha_debriefing | C91: Marketing e campanhas | D91: 3 | E91: campanha_id | F91: uuid | G91: sim | I91: UNIQUE | J91: campanhas.id | L91: =IFERROR(VLOOKUP(IF(ISNUMBER(SEARCH("(",F91)),LEFT(F91,SEARCH("(",F91)-1),F91),Tipos!$A:$B,2,FALSE()),"outro") -> uuid | M91: =IF(COUNTIF(Comparação!$H:$H,A91)>0,"sim",IF(AND(G91="sim",H91=""),"FALTA (obrigatória)","não")) -> FALTA (obrigatória)
A92: =B92&"."&E92 -> campanha_debriefing.resultado | B92: campanha_debriefing | C92: Marketing e campanhas | D92: 4 | E92: resultado | F92: text | G92: não | L92: =IFERROR(VLOOKUP(IF(ISNUMBER(SEARCH("(",F92)),LEFT(F92,SEARCH("(",F92)-1),F92),Tipos!$A:$B,2,FALSE()),"outro") -> texto | M92: =IF(COUNTIF(Comparação!$H:$H,A92)>0,"sim",IF(AND(G92="sim",H92=""),"FALTA (obrigatória)","não")) -> não
A93: =B93&"."&E93 -> campanha_debriefing.funcionou | B93: campanha_debriefing | C93: Marketing e campanhas | D93: 5 | E93: funcionou | F93: text | G93: não | L93: =IFERROR(VLOOKUP(IF(ISNUMBER(SEARCH("(",F93)),LEFT(F93,SEARCH("(",F93)-1),F93),Tipos!$A:$B,2,FALSE()),"outro") -> texto | M93: =IF(COUNTIF(Comparação!$H:$H,A93)>0,"sim",IF(AND(G93="sim",H93=""),"FALTA (obrigatória)","não")) -> não
A94: =B94&"."&E94 -> campanha_debriefing.nao_funcionou | B94: campanha_debriefing | C94: Marketing e campanhas | D94: 6 | E94: nao_funcionou | F94: text | G94: não | L94: =IFERROR(VLOOKUP(IF(ISNUMBER(SEARCH("(",F94)),LEFT(F94,SEARCH("(",F94)-1),F94),Tipos!$A:$B,2,FALSE()),"outro") -> texto | M94: =IF(COUNTIF(Comparação!$H:$H,A94)>0,"sim",IF(AND(G94="sim",H94=""),"FALTA (obrigatória)","não")) -> não
A95: =B95&"."&E95 -> campanha_debriefing.aprendizados | B95: campanha_debriefing | C95: Marketing e campanhas | D95: 7 | E95: aprendizados | F95: text | G95: não | L95: =IFERROR(VLOOKUP(IF(ISNUMBER(SEARCH("(",F95)),LEFT(F95,SEARCH("(",F95)-1),F95),Tipos!$A:$B,2,FALSE()),"outro") -> texto | M95: =IF(COUNTIF(Comparação!$H:$H,A95)>0,"sim",IF(AND(G95="sim",H95=""),"FALTA (obrigatória)","não")) -> não
A96: =B96&"."&E96 -> campanha_debriefing.proximos_passos | B96: campanha_debriefing | C96: Marketing e campanhas | D96: 8 | E96: proximos_passos | F96: text | G96: não | L96: =IFERROR(VLOOKUP(IF(ISNUMBER(SEARCH("(",F96)),LEFT(F96,SEARCH("(",F96)-1),F96),Tipos!$A:$B,2,FALSE()),"outro") -> texto | M96: =IF(COUNTIF(Comparação!$H:$H,A96)>0,"sim",IF(AND(G96="sim",H96=""),"FALTA (obrigatória)","não")) -> não
A97: =B97&"."&E97 -> campanha_debriefing.atualizado_em | B97: campanha_debriefing | C97: Marketing e campanhas | D97: 9 | E97: atualizado_em | F97: timestamptz | G97: sim | H97: now() | L97: =IFERROR(VLOOKUP(IF(ISNUMBER(SEARCH("(",F97)),LEFT(F97,SEARCH("(",F97)-1),F97),Tipos!$A:$B,2,FALSE()),"outro") -> data e hora | M97: =IF(COUNTIF(Comparação!$H:$H,A97)>0,"sim",IF(AND(G97="sim",H97=""),"FALTA (obrigatória)","não")) -> não
A98: =B98&"."&E98 -> campanha_estrategias.id | B98: campanha_estrategias | C98: Marketing e campanhas | D98: 1 | E98: id | F98: uuid | G98: sim | H98: gen_random_uuid() | I98: PRIMARY KEY | L98: =IFERROR(VLOOKUP(IF(ISNUMBER(SEARCH("(",F98)),LEFT(F98,SEARCH("(",F98)-1),F98),Tipos!$A:$B,2,FALSE()),"outro") -> uuid | M98: =IF(COUNTIF(Comparação!$H:$H,A98)>0,"sim",IF(AND(G98="sim",H98=""),"FALTA (obrigatória)","não")) -> não
A99: =B99&"."&E99 -> campanha_estrategias.workspace_id | B99: campanha_estrategias | C99: Marketing e campanhas | D99: 2 | E99: workspace_id | F99: uuid | G99: sim | J99: workspaces.id | L99: =IFERROR(VLOOKUP(IF(ISNUMBER(SEARCH("(",F99)),LEFT(F99,SEARCH("(",F99)-1),F99),Tipos!$A:$B,2,FALSE()),"outro") -> uuid | M99: =IF(COUNTIF(Comparação!$H:$H,A99)>0,"sim",IF(AND(G99="sim",H99=""),"FALTA (obrigatória)","não")) -> FALTA (obrigatória)
A100: =B100&"."&E100 -> campanha_estrategias.campanha_id | B100: campanha_estrategias | C100: Marketing e campanhas | D100: 3 | E100: campanha_id | F100: uuid | G100: sim | I100: UNIQUE | J100: campanhas.id | L100: =IFERROR(VLOOKUP(IF(ISNUMBER(SEARCH("(",F100)),LEFT(F100,SEARCH("(",F100)-1),F100),Tipos!$A:$B,2,FALSE()),"outro") -> uuid | M100: =IF(COUNTIF(Comparação!$H:$H,A100)>0,"sim",IF(AND(G100="sim",H100=""),"FALTA (obrigatória)","não")) -> FALTA (obrigatória)
...

Sheet Tipos
A1: Tipo (como aparece) | B1: Família
A2: text | B2: texto
A3: varchar | B3: texto
A4: character varying | B4: texto
A5: character | B5: texto
A6: char | B6: texto
A7: nvarchar | B7: texto
A8: nchar | B8: texto
A9: citext | B9: texto
A10: longtext | B10: texto
A11: mediumtext | B11: texto
A12: tinytext | B12: texto
... A59: _jsonb | B59: lista

Sheet Outro banco
A1: tabela | B1: coluna | C1: tipo | D1: obrigatório
A2: (cole aqui o resultado da consulta, a partir desta linha)

Sheet Comparação
A1: Tabela (outro banco) | B1: Coluna (outro banco) | C1: Tipo (outro banco) | D1: Obrigatório (outro) | E1: Tabela no Growths (mude se o nome for outro) | F1: Coluna no Growths (mude se o nome for outro) | G1: Tabela existe? | H1: Chave Growths | I1: Tipo no Growths | J1: Família outro | K1: Família Growths | L1: Status | M1: Observação
A2: =IF('Outro banco'!A2="","",IF(LEFT('Outro banco'!A2,1)="(","",'Outro banco'!A2)) | B2: =IF(A2="","",'Outro banco'!B2) | C2: =IF(A2="","",'Outro banco'!C2) | D2: =IF(A2="","",'Outro banco'!D2) | G2: =IF(A2="","",IF(COUNTIF(Tabelas!$A:$A,IF(E2="",A2,E2))>0,"sim","não")) | H2: =IF(A2="","",IF(E2="",A2,E2)&"."&IF(F2="",B2,F2)) | I2: =IF(A2="","",IFERROR(INDEX('Campos Growths'!$F:$F,MATCH(H2,'Campos Growths'!$A:$A,0)),"")) | J2: =IF(A2="","",IFERROR(VLOOKUP(IF(ISNUMBER(SEARCH("(",C2)),LEFT(C2,SEARCH("(",C2)-1),C2),Tipos!$A:$B,2,FALSE()),"outro")) | K2: =IF(I2="","",IFERROR(INDEX('Campos Growths'!$L:$L,MATCH(H2,'Campos Growths'!$A:$A,0)),"")) | L2: =IF(A2="","",IF(G2="não","Sem tabela no Growths",IF(I2="","Sem campo no Growths",IF(J2=K2,"Importa direto","Ajustar tipo"))))
A3: =IF('Outro banco'!A3="","",IF(LEFT('Outro banco'!A3,1)="(","",'Outro banco'!A3)) | B3: =IF(A3="","",'Outro banco'!B3) | C3: =IF(A3="","",'Outro banco'!C3) | D3: =IF(A3="","",'Outro banco'!D3) | G3: =IF(A3="","",IF(COUNTIF(Tabelas!$A:$A,IF(E3="",A3,E3))>0,"sim","não")) | H3: =IF(A3="","",IF(E3="",A3,E3)&"."&IF(F3="",B3,F3)) | I3: =IF(A3="","",IFERROR(INDEX('Campos Growths'!$F:$F,MATCH(H3,'Campos Growths'!$A:$A,0)),"")) | J3: =IF(A3="","",IFERROR(VLOOKUP(IF(ISNUMBER(SEARCH("(",C3)),LEFT(C3,SEARCH("(",C3)-1),C3),Tipos!$A:$B,2,FALSE()),"outro")) | K3: =IF(I3="","",IFERROR(INDEX('Campos Growths'!$L:$L,MATCH(H3,'Campos Growths'!$A:$A,0)),"")) | L3: =IF(A3="","",IF(G3="não","Sem tabela no Growths",IF(I3="","Sem campo no Growths",IF(J3=K3,"Importa direto","Ajustar tipo"))))
A4: =IF('Outro banco'!A4="","",IF(LEFT('Outro banco'!A4,1)="(","",'Outro banco'!A4)) | B4: =IF(A4="","",'Outro banco'!B4) | C4: =IF(A4="","",'Outro banco'!C4) | D4: =IF(A4="","",'Outro banco'!D4) | G4: =IF(A4="","",IF(COUNTIF(Tabelas!$A:$A,IF(E4="",A4,E4))>0,"sim","não")) | H4: =IF(A4="","",IF(E4="",A4,E4)&"."&IF(F4="",B4,F4)) | I4: =IF(A4="","",IFERROR(INDEX('Campos Growths'!$F:$F,MATCH(H4,'Campos Growths'!$A:$A,0)),"")) | J4: =IF(A4="","",IFERROR(VLOOKUP(IF(ISNUMBER(SEARCH("(",C4)),LEFT(C4,SEARCH("(",C4)-1),C4),Tipos!$A:$B,2,FALSE()),"outro")) | K4: =IF(I4="","",IFERROR(INDEX('Campos Growths'!$L:$L,MATCH(H4,'Campos Growths'!$A:$A,0)),"")) | L4: =IF(A4="","",IF(G4="não","Sem tabela no Growths",IF(I4="","Sem campo no Growths",IF(J4=K4,"Importa direto","Ajustar tipo"))))
A5: =IF('Outro banco'!A5="","",IF(LEFT('Outro banco'!A5,1)="(","",'Outro banco'!A5)) | B5: =IF(A5="","",'Outro banco'!B5) | C5: =IF(A5="","",'Outro banco'!C5) | D5: =IF(A5="","",'Outro banco'!D5) | G5: =IF(A5="","",IF(COUNTIF(Tabelas!$A:$A,IF(E5="",A5,E5))>0,"sim","não")) | H5: =IF(A5="","",IF(E5="",A5,E5)&"."&IF(F5="",B5,F5)) | I5: =IF(A5="","",IFERROR(INDEX('Campos Growths'!$F:$F,MATCH(H5,'Campos Growths'!$A:$A,0)),"")) | J5: =IF(A5="","",IFERROR(VLOOKUP(IF(ISNUMBER(SEARCH("(",C5)),LEFT(C5,SEARCH("(",C5)-1),C5),Tipos!$A:$B,2,FALSE()),"outro")) | K5: =IF(I5="","",IFERROR(INDEX('Campos Growths'!$L:$L,MATCH(H5,'Campos Growths'!$A:$A,0)),"")) | L5: =IF(A5="","",IF(G5="não","Sem tabela no Growths",IF(I5="","Sem campo no Growths",IF(J5=K5,"Importa direto","Ajustar tipo"))))
A6: =IF('Outro banco'!A6="","",IF(LEFT('Outro banco'!A6,1)="(","",'Outro banco'!A6)) | B6: =IF(A6="","",'Outro banco'!B6) | C6: =IF(A6="","",'Outro banco'!C6) | D6: =IF(A6="","",'Outro banco'!D6) | G6: =IF(A6="","",IF(COUNTIF(Tabelas!$A:$A,IF(E6="",A6,E6))>0,"sim","não")) | H6: =IF(A6="","",IF(E6="",A6,E6)&"."&IF(F6="",B6,F6)) | I6: =IF(A6="","",IFERROR(INDEX('Campos Growths'!$F:$F,MATCH(H6,'Campos Growths'!$A:$A,0)),"")) | J6: =IF(A6="","",IFERROR(VLOOKUP(IF(ISNUMBER(SEARCH("(",C6)),LEFT(C6,SEARCH("(",C6)-1),C6),Tipos!$A:$B,2,FALSE()),"outro")) | K6: =IF(I6="","",IFERROR(INDEX('Campos Growths'!$L:$L,MATCH(H6,'Campos Growths'!$A:$A,0)),"")) | L6: =IF(A6="","",IF(G6="não","Sem tabela no Growths",IF(I6="","Sem campo no Growths",IF(J6=K6,"Importa direto","Ajustar tipo"))))
A7: =IF('Outro banco'!A7="","",IF(LEFT('Outro banco'!A7,1)="(","",'Outro banco'!A7)) | B7: =IF(A7="","",'Outro banco'!B7) | C7: =IF(A7="","",'Outro banco'!C7) | D7: =IF(A7="","",'Outro banco'!D7) | G7: =IF(A7="","",IF(COUNTIF(Tabelas!$A:$A,IF(E7="",A7,E7))>0,"sim","não")) | H7: =IF(A7="","",IF(E7="",A7,E7)&"."&IF(F7="",B7,F7)) | I7: =IF(A7="","",IFERROR(INDEX('Campos Growths'!$F:$F,MATCH(H7,'Campos Growths'!$A:$A,0)),"")) | J7: =IF(A7="","",IFERROR(VLOOKUP(IF(ISNUMBER(SEARCH("(",C7)),LEFT(C7,SEARCH("(",C7)-1),C7),Tipos!$A:$B,2,FALSE()),"outro")) | K7: =IF(I7="","",IFERROR(INDEX('Campos Growths'!$L:$L,MATCH(H7,'Campos Growths'!$A:$A,0)),"")) | L7: =IF(A7="","",IF(G7="não","Sem tabela no Growths",IF(I7="","Sem campo no Growths",IF(J7=K7,"Importa direto","Ajustar tipo"))))
A8: =IF('Outro banco'!A8="","",IF(LEFT('Outro banco'!A8,1)="(","",'Outro banco'!A8)) | B8: =IF(A8="","",'Outro banco'!B8) | C8: =IF(A8="","",'Outro banco'!C8) | D8: =IF(A8="","",'Outro banco'!D8) | G8: =IF(A8="","",IF(COUNTIF(Tabelas!$A:$A,IF(E8="",A8,E8))>0,"sim","não")) | H8: =IF(A8="","",IF(E8="",A8,E8)&"."&IF(F8="",B8,F8)) | I8: =IF(A8="","",IFERROR(INDEX('Campos Growths'!$F:$F,MATCH(H8,'Campos Growths'!$A:$A,0)),"")) | J8: =IF(A8="","",IFERROR(VLOOKUP(IF(ISNUMBER(SEARCH("(",C8)),LEFT(C8,SEARCH("(",C8)-1),C8),Tipos!$A:$B,2,FALSE()),"outro")) | K8: =IF(I8="","",IFERROR(INDEX('Campos Growths'!$L:$L,MATCH(H8,'Campos Growths'!$A:$A,0)),"")) | L8: =IF(A8="","",IF(G8="não","Sem tabela no Growths",IF(I8="","Sem campo no Growths",IF(J8=K8,"Importa direto","Ajustar tipo"))))
A9: =IF('Outro banco'!A9="","",IF(LEFT('Outro banco'!A9,1)="(","",'Outro banco'!A9)) | B9: =IF(A9="","",'Outro banco'!B9) | C9: =IF(A9="","",'Outro banco'!C9) | D9: =IF(A9="","",'Outro banco'!D9) | G9: =IF(A9="","",IF(COUNTIF(Tabelas!$A:$A,IF(E9="",A9,E9))>0,"sim","não")) | H9: =IF(A9="","",IF(E9="",A9,E9)&"."&IF(F9="",B9,F9)) | I9: =IF(A9="","",IFERROR(INDEX('Campos Growths'!$F:$F,MATCH(H9,'Campos Growths'!$A:$A,0)),"")) | J9: =IF(A9="","",IFERROR(VLOOKUP(IF(ISNUMBER(SEARCH("(",C9)),LEFT(C9,SEARCH("(",C9)-1),C9),Tipos!$A:$B,2,FALSE()),"outro")) | K9: =IF(I9="","",IFERROR(INDEX('Campos Growths'!$L:$L,MATCH(H9,'Campos Growths'!$A:$A,0)),"")) | L9: =IF(A9="","",IF(G9="não","Sem tabela no Growths",IF(I9="","Sem campo no Growths",IF(J9=K9,"Importa direto","Ajustar tipo"))))
A10: =IF('Outro banco'!A10="","",IF(LEFT('Outro banco'!A10,1)="(","",'Outro banco'!A10)) | B10: =IF(A10="","",'Outro banco'!B10) | C10: =IF(A10="","",'Outro banco'!C10) | D10: =IF(A10="","",'Outro banco'!D10) | G10: =IF(A10="","",IF(COUNTIF(Tabelas!$A:$A,IF(E10="",A10,E10))>0,"sim","não")) | H10: =IF(A10="","",IF(E10="",A10,E10)&"."&IF(F10="",B10,F10)) | I10: =IF(A10="","",IFERROR(INDEX('Campos Growths'!$F:$F,MATCH(H10,'Campos Growths'!$A:$A,0)),"")) | J10: =IF(A10="","",IFERROR(VLOOKUP(IF(ISNUMBER(SEARCH("(",C10)),LEFT(C10,SEARCH("(",C10)-1),C10),Tipos!$A:$B,2,FALSE()),"outro")) | K10: =IF(I10="","",IFERROR(INDEX('Campos Growths'!$L:$L,MATCH(H10,'Campos Growths'!$A:$A,0)),"")) | L10: =IF(A10="","",IF(G10="não","Sem tabela no Growths",IF(I10="","Sem campo no Growths",IF(J10=K10,"Importa direto","Ajustar tipo"))))
A11: =IF('Outro banco'!A11="","",IF(LEFT('Outro banco'!A11,1)="(","",'Outro banco'!A11)) | B11: =IF(A11="","",'Outro banco'!B11) | C11: =IF(A11="","",'Outro banco'!C11) | D11: =IF(A11="","",'Outro banco'!D11) | G11: =IF(A11="","",IF(COUNTIF(Tabelas!$A:$A,IF(E11="",A11,E11))>0,"sim","não")) | H11: =IF(A11="","",IF(E11="",A11,E11)&"."&IF(F11="",B11,F11)) | I11: =IF(A11="","",IFERROR(INDEX('Campos Growths'!$F:$F,MATCH(H11,'Campos Growths'!$A:$A,0)),"")) | J11: =IF(A11="","",IFERROR(VLOOKUP(IF(ISNUMBER(SEARCH("(",C11)),LEFT(C11,SEARCH("(",C11)-1),C11),Tipos!$A:$B,2,FALSE()),"outro")) | K11: =IF(I11="","",IFERROR(INDEX('Campos Growths'!$L:$L,MATCH(H11,'Campos Growths'!$A:$A,0)),"")) | L11: =IF(A11="","",IF(G11="não","Sem tabela no Growths",IF(I11="","Sem campo no Growths",IF(J11=K11,"Importa direto","Ajustar tipo"))))
A12: =IF('Outro banco'!A12="","",IF(LEFT('Outro banco'!A12,1)="(","",'Outro banco'!A12)) | B12: =IF(A12="","",'Outro banco'!B12) | C12: =IF(A12="","",'Outro banco'!C12) | D12: =IF(A12="","",'Outro banco'!D12) | G12: =IF(A12="","",IF(COUNTIF(Tabelas!$A:$A,IF(E12="",A12,E12))>0,"sim","não")) | H12: =IF(A12="","",IF(E12="",A12,E12)&"."&IF(F12="",B12,F12)) | I12: =IF(A12="","",IFERROR(INDEX('Campos Growths'!$F:$F,MATCH(H12,'Campos Growths'!$A:$A,0)),"")) | J12: =IF(A12="","",IFERROR(VLOOKUP(IF(ISNUMBER(SEARCH("(",C12)),LEFT(C12,SEARCH("(",C12)-1),C12),Tipos!$A:$B,2,FALSE()),"outro")) | K12: =IF(I12="","",IFERROR(INDEX('Campos Growths'!$L:$L,MATCH(H12,'Campos Growths'!$A:$A,0)),"")) | L12: =IF(A12="","",IF(G12="não","Sem tabela no Growths",IF(I12="","Sem campo no Growths",IF(J12=K12,"Importa direto","Ajustar tipo"))))
A13: =IF('Outro banco'!A13="","",IF(LEFT('Outro banco'!A13,1)="(","",'Outro banco'!A13)) | B13: =IF(A13="","",'Outro banco'!B13) | C13: =IF(A13="","",'Outro banco'!C13) | D13: =IF(A13="","",'Outro banco'!D13) | G13: =IF(A13="","",IF(COUNTIF(Tabelas!$A:$A,IF(E13="",A13,E13))>0,"sim","não")) | H13: =IF(A13="","",IF(E13="",A13,E13)&"."&IF(F13="",B13,F13)) | I13: =IF(A13="","",IFERROR(INDEX('Campos Growths'!$F:$F,MATCH(H13,'Campos Growths'!$A:$A,0)),"")) | J13: =IF(A13="","",IFERROR(VLOOKUP(IF(ISNUMBER(SEARCH("(",C13)),LEFT(C13,SEARCH("(",C13)-1),C13),Tipos!$A:$B,2,FALSE()),"outro")) | K13: =IF(I13="","",IFERROR(INDEX('Campos Growths'!$L:$L,MATCH(H13,'Campos Growths'!$A:$A,0)),"")) | L13: =IF(A13="","",IF(G13="não","Sem tabela no Growths",IF(I13="","Sem campo no Growths",IF(J13=K13,"Importa direto","Ajustar tipo"))))
... A3001: =IF('Outro banco'!A3001="","",IF(LEFT('Outro banco'!A3001,1)="(","",'Outro banco'!A3001)) | B3001: =IF(A3001="","",'Outro banco'!B3001) | C3001: =IF(A3001="","",'Outro banco'!C3001) | D3001: =IF(A3001="","",'Outro banco'!D3001) | G3001: =IF(A3001="","",IF(COUNTIF(Tabelas!$A:$A,IF(E3001="",A3001,E3001))>0,"sim","não")) | H3001: =IF(A3001="","",IF(E3001="",A3001,E3001)&"."&IF(F3001="",B3001,F3001)) | I3001: =IF(A3001="","",IFERROR(INDEX('Campos Growths'!$F:$F,MATCH(H3001,'Campos Growths'!$A:$A,0)),"")) | J3001: =IF(A3001="","",IFERROR(VLOOKUP(IF(ISNUMBER(SEARCH("(",C3001)),LEFT(C3001,SEARCH("(",C3001)-1),C3001),Tipos!$A:$B,2,FALSE()),"outro")) | K3001: =IF(I3001="","",IFERROR(INDEX('Campos Growths'!$L:$L,MATCH(H3001,'Campos Growths'!$A:$A,0)),"")) | L3001: =IF(A3001="","",IF(G3001="não","Sem tabela no Growths",IF(I3001="","Sem campo no Growths",IF(J3001=K3001,"Importa direto","Ajustar tipo"))))
